coursebox/__init__.py
coursebox/setup_coursebox.py
coursebox/thtools_base.py
coursebox/admin/__init__.py
coursebox/admin/gitlab.py
coursebox/book/__init__.py
coursebox/book/exam_includer.py
coursebox/core/__init__.py
coursebox/core/course.py
coursebox/core/info.py
coursebox/core/info_paths.py
coursebox/core/projects.py
coursebox/core/projects_info.py
coursebox/core/projects_plagiarism.py
coursebox/material/__init__.py
coursebox/material/documentation.py
coursebox/material/homepage_lectures_exercises.py
coursebox/material/lecture_questions.py
coursebox/material/snipper.py
coursebox/student_files/__init__.py
coursebox/student_files/student_files.py
coursebox/testing/__init__.py
coursebox/testing/testing.py
coursebox-0.1.20.14.dist-info/LICENSE
coursebox-0.1.20.14.dist-info/METADATA
coursebox-0.1.20.14.dist-info/WHEEL
coursebox-0.1.20.14.dist-info/top_level.txt
coursebox-0.1.20.14.dist-info/RECORD
