Metadata-Version: 2.2
Name: coursebox
Version: 0.1.20.14
Summary: A course management system currently used at DTU
Home-page: https://lab.compute.dtu.dk/tuhe/coursebox
Author: Tue Herlau
Author-email: tuhe@dtu.dk
License: MIT
Project-URL: Bug Tracker, https://lab.compute.dtu.dk/tuhe/coursebox/issues
Classifier: Programming Language :: Python :: 3
Classifier: License :: OSI Approved :: MIT License
Classifier: Operating System :: OS Independent
Requires-Python: >=3.8
License-File: LICENSE
Requires-Dist: numpy
Requires-Dist: pycode_similar
Requires-Dist: tika
Requires-Dist: openpyxl
Requires-Dist: xlwings
Requires-Dist: matplotlib
Requires-Dist: langdetect
Requires-Dist: beamer-slider
Requires-Dist: tinydb
Requires-Dist: python-gitlab
Dynamic: author
Dynamic: author-email
Dynamic: classifier
Dynamic: description
Dynamic: description-content-type
Dynamic: home-page
Dynamic: license
Dynamic: project-url
Dynamic: requires-dist
Dynamic: requires-python
Dynamic: summary
